HISTORY.txt
LICENSE
MANIFEST.in
README.rst
setup.py
tox.ini
bin/.gitignore
bin/cibuild
docxcompose/__init__.py
docxcompose/command.py
docxcompose/composer.py
docxcompose/image.py
docxcompose/properties.py
docxcompose/sdt.py
docxcompose/utils.py
docxcompose.egg-info/PKG-INFO
docxcompose.egg-info/SOURCES.txt
docxcompose.egg-info/dependency_links.txt
docxcompose.egg-info/entry_points.txt
docxcompose.egg-info/requires.txt
docxcompose.egg-info/top_level.txt
docxcompose.egg-info/zip-safe
docxcompose/templates/custom.xml
docxcompose/templates/footer.xml
docxcompose/templates/footnotes.xml
docxcompose/templates/header.xml
docxcompose/templates/numbering.xml