Metadata-Version: 1.1
Name: docxcompose
Version: 1.0.0
Summary: Compose .docx documents
Home-page: https://github.com/4teamwork/docxcompose
Author: Thomas Buchberger
Author-email: t.buchberger@4teamwork.ch
License: MIT license
Keywords: Python DOCX Word OOXML
Platform: UNKNOWN
Classifier: Programming Language :: Python
Classifier: Programming Language :: Python :: 2.7
Classifier: Programming Language :: Python :: 3
Classifier: Operating System :: OS Independent
Classifier: License :: OSI Approved :: MIT License
